{"operations": [{"end": 1466559483, "status_code": "GOOD", "start": 1466559141, "subdir": "sysbench.cpu", "duration": 342, "message": "", "localtime": "6\u6708 22 09:32:21"}], "operations_executed": 1, "report_generation_time": "Wed Jun 22 09:38:03 2016", "job_passed": true, "sysinfo": {"uname": "Linux isoft_lp 4.4.1-1 #1 SMP Tue Feb 2 14:09:15 CST 2016 x86_64 GNU/Linux\n<br>", "gcc": "gcc (GCC) 5.3.0 20151204 (iSoft 5.3.0-12)\n<br>Copyright \u00a9 2015 Free Software Foundation, Inc.\n<br>\u672c\u7a0b\u5e8f\u662f\u81ea\u7531\u8f6f\u4ef6\uff1b\u8bf7\u53c2\u770b\u6e90\u4ee3\u7801\u7684\u7248\u6743\u58f0\u660e\u3002\u672c\u8f6f\u4ef6\u6ca1\u6709\u4efb\u4f55\u62c5\u4fdd\uff1b\n<br>\u5305\u62ec\u6ca1\u6709\u9002\u9500\u6027\u548c\u67d0\u4e00\u4e13\u7528\u76ee\u7684\u4e0b\u7684\u9002\u7528\u6027\u62c5\u4fdd\u3002\n<br>", "dmesg": "File not found.<br>", "meminfo": "MemTotal:        3761304 kB\n<br>MemFree:          442948 kB\n<br>MemAvailable:    1267776 kB\n<br>Buffers:           15508 kB\n<br>Cached:          1302692 kB\n<br>SwapCached:            0 kB\n<br>Active:          2046968 kB\n<br>Inactive:        1005624 kB\n<br>Active(anon):    1531000 kB\n<br>Inactive(anon):   743608 kB\n<br>Active(file):     515968 kB\n<br>Inactive(file):   262016 kB\n<br>Unevictable:          96 kB\n<br>Mlocked:              96 kB\n<br>SwapTotal:       4194300 kB\n<br>SwapFree:        4194020 kB\n<br>Dirty:             12068 kB\n<br>Writeback:             0 kB\n<br>AnonPages:       1734756 kB\n<br>Mapped:           815624 kB\n<br>Shmem:            539916 kB\n<br>Slab:             126028 kB\n<br>SReclaimable:      75500 kB\n<br>SUnreclaim:        50528 kB\n<br>KernelStack:        8416 kB\n<br>PageTables:        54296 kB\n<br>NFS_Unstable:          0 kB\n<br>Bounce:                0 kB\n<br>WritebackTmp:          0 kB\n<br>CommitLimit:     6074952 kB\n<br>Committed_AS:    5813236 kB\n<br>VmallocTotal:   34359738367 kB\n<br>VmallocUsed:           0 kB\n<br>VmallocChunk:          0 kB\n<br>AnonHugePages:    393216 kB\n<br>HugePages_Total:       0\n<br>HugePages_Free:        0\n<br>HugePages_Rsvd:        0\n<br>HugePages_Surp:        0\n<br>Hugepagesize:       2048 kB\n<br>DirectMap4k:       38336 kB\n<br>DirectMap2M:     1769472 kB\n<br>DirectMap1G:     3145728 kB\n<br>", "cpuinfo": "processor\t: 0\n<br>vendor_id\t: GenuineIntel\n<br>cpu family\t: 6\n<br>model\t\t: 69\n<br>model name\t: Intel(R) Core(TM) i5-4200U CPU @ 1.60GHz\n<br>stepping\t: 1\n<br>microcode\t: 0x15\n<br>cpu MHz\t\t: 2567.015\n<br>cache size\t: 3072 KB\n<br>physical id\t: 0\n<br>siblings\t: 4\n<br>core id\t\t: 0\n<br>cpu cores\t: 2\n<br>apicid\t\t: 0\n<br>initial apicid\t: 0\n<br>fpu\t\t: yes\n<br>fpu_exception\t: yes\n<br>cpuid level\t: 13\n<br>wp\t\t: yes\n<br>flags\t\t: fpu vme de pse tsc msr pae mce cx8 apic sep mtrr pge mca cmov pat pse36 clflush dts acpi mmx fxsr sse sse2 ss ht tm pbe syscall nx pdpe1gb rdtscp lm constant_tsc arch_perfmon pebs bts rep_good nopl xtopology nonstop_tsc aperfmperf eagerfpu pni pclmulqdq dtes64 monitor ds_cpl vmx est tm2 ssse3 sdbg fma cx16 xtpr pdcm pcid sse4_1 sse4_2 movbe popcnt tsc_deadline_timer aes xsave avx f16c rdrand lahf_lm abm ida arat epb pln pts dtherm tpr_shadow vnmi flexpriority ept vpid fsgsbase tsc_adjust bmi1 avx2 smep bmi2 erms invpcid xsaveopt\n<br>bugs\t\t:\n<br>bogomips\t: 4589.35\n<br>clflush size\t: 64\n<br>cache_alignment\t: 64\n<br>address sizes\t: 39 bits physical, 48 bits virtual\n<br>power management:\n<br>\n<br>processor\t: 1\n<br>vendor_id\t: GenuineIntel\n<br>cpu family\t: 6\n<br>model\t\t: 69\n<br>model name\t: Intel(R) Core(TM) i5-4200U CPU @ 1.60GHz\n<br>stepping\t: 1\n<br>microcode\t: 0x15\n<br>cpu MHz\t\t: 2584.355\n<br>cache size\t: 3072 KB\n<br>physical id\t: 0\n<br>siblings\t: 4\n<br>core id\t\t: 0\n<br>cpu cores\t: 2\n<br>apicid\t\t: 1\n<br>initial apicid\t: 1\n<br>fpu\t\t: yes\n<br>fpu_exception\t: yes\n<br>cpuid level\t: 13\n<br>wp\t\t: yes\n<br>flags\t\t: fpu vme de pse tsc msr pae mce cx8 apic sep mtrr pge mca cmov pat pse36 clflush dts acpi mmx fxsr sse sse2 ss ht tm pbe syscall nx pdpe1gb rdtscp lm constant_tsc arch_perfmon pebs bts rep_good nopl xtopology nonstop_tsc aperfmperf eagerfpu pni pclmulqdq dtes64 monitor ds_cpl vmx est tm2 ssse3 sdbg fma cx16 xtpr pdcm pcid sse4_1 sse4_2 movbe popcnt tsc_deadline_timer aes xsave avx f16c rdrand lahf_lm abm ida arat epb pln pts dtherm tpr_shadow vnmi flexpriority ept vpid fsgsbase tsc_adjust bmi1 avx2 smep bmi2 erms invpcid xsaveopt\n<br>bugs\t\t:\n<br>bogomips\t: 4589.35\n<br>clflush size\t: 64\n<br>cache_alignment\t: 64\n<br>address sizes\t: 39 bits physical, 48 bits virtual\n<br>power management:\n<br>\n<br>processor\t: 2\n<br>vendor_id\t: GenuineIntel\n<br>cpu family\t: 6\n<br>model\t\t: 69\n<br>model name\t: Intel(R) Core(TM) i5-4200U CPU @ 1.60GHz\n<br>stepping\t: 1\n<br>microcode\t: 0x15\n<br>cpu MHz\t\t: 2410.328\n<br>cache size\t: 3072 KB\n<br>physical id\t: 0\n<br>siblings\t: 4\n<br>core id\t\t: 1\n<br>cpu cores\t: 2\n<br>apicid\t\t: 2\n<br>initial apicid\t: 2\n<br>fpu\t\t: yes\n<br>fpu_exception\t: yes\n<br>cpuid level\t: 13\n<br>wp\t\t: yes\n<br>flags\t\t: fpu vme de pse tsc msr pae mce cx8 apic sep mtrr pge mca cmov pat pse36 clflush dts acpi mmx fxsr sse sse2 ss ht tm pbe syscall nx pdpe1gb rdtscp lm constant_tsc arch_perfmon pebs bts rep_good nopl xtopology nonstop_tsc aperfmperf eagerfpu pni pclmulqdq dtes64 monitor ds_cpl vmx est tm2 ssse3 sdbg fma cx16 xtpr pdcm pcid sse4_1 sse4_2 movbe popcnt tsc_deadline_timer aes xsave avx f16c rdrand lahf_lm abm ida arat epb pln pts dtherm tpr_shadow vnmi flexpriority ept vpid fsgsbase tsc_adjust bmi1 avx2 smep bmi2 erms invpcid xsaveopt\n<br>bugs\t\t:\n<br>bogomips\t: 4589.35\n<br>clflush size\t: 64\n<br>cache_alignment\t: 64\n<br>address sizes\t: 39 bits physical, 48 bits virtual\n<br>power management:\n<br>\n<br>processor\t: 3\n<br>vendor_id\t: GenuineIntel\n<br>cpu family\t: 6\n<br>model\t\t: 69\n<br>model name\t: Intel(R) Core(TM) i5-4200U CPU @ 1.60GHz\n<br>stepping\t: 1\n<br>microcode\t: 0x15\n<br>cpu MHz\t\t: 2564.859\n<br>cache size\t: 3072 KB\n<br>physical id\t: 0\n<br>siblings\t: 4\n<br>core id\t\t: 1\n<br>cpu cores\t: 2\n<br>apicid\t\t: 3\n<br>initial apicid\t: 3\n<br>fpu\t\t: yes\n<br>fpu_exception\t: yes\n<br>cpuid level\t: 13\n<br>wp\t\t: yes\n<br>flags\t\t: fpu vme de pse tsc msr pae mce cx8 apic sep mtrr pge mca cmov pat pse36 clflush dts acpi mmx fxsr sse sse2 ss ht tm pbe syscall nx pdpe1gb rdtscp lm constant_tsc arch_perfmon pebs bts rep_good nopl xtopology nonstop_tsc aperfmperf eagerfpu pni pclmulqdq dtes64 monitor ds_cpl vmx est tm2 ssse3 sdbg fma cx16 xtpr pdcm pcid sse4_1 sse4_2 movbe popcnt tsc_deadline_timer aes xsave avx f16c rdrand lahf_lm abm ida arat epb pln pts dtherm tpr_shadow vnmi flexpriority ept vpid fsgsbase tsc_adjust bmi1 avx2 smep bmi2 erms invpcid xsaveopt\n<br>bugs\t\t:\n<br>bogomips\t: 4589.35\n<br>clflush size\t: 64\n<br>cache_alignment\t: 64\n<br>address sizes\t: 39 bits physical, 48 bits virtual\n<br>power management:\n<br>\n<br>", "df": "\u6587\u4ef6\u7cfb\u7edf       1048576-\u5757  \u5df2\u7528  \u53ef\u7528 \u914d\u989d \u6302\u8f7d\u70b9\n<br>devtmpfs             1821     0  1821   0% /dev\n<br>tmpfs                1837    42  1795   3% /dev/shm\n<br>tmpfs                1837     2  1836   1% /run\n<br>tmpfs                1837     0  1837   0% /sys/fs/cgroup\n<br>/dev/sda13          93786 69806 23964  75% /\n<br>tmpfs                1837   297  1540  17% /tmp\n<br>/dev/sda12            189     1   188   1% /boot/efi\n<br>tmpfs                 368     0   368   0% /run/user/987\n<br>tmpfs                 368     1   368   1% /run/user/1000\n<br>/dev/sda7          100000 76902 23099  77% /run/media/isoft_lp/\u6587\u6863\u4e0e\u8d44\u6599\n<br>", "dmidecode": "# dmidecode 2.12\n<br># SMBIOS entry point at 0x90ebef98\n<br>SMBIOS 2.7 present.\n<br>73 structures occupying 3068 bytes.\n<br>Table at 0x90EBC000.\n<br>\n<br>Handle 0x0000, DMI type 0, 24 bytes\n<br>BIOS Information\n<br>\tVendor: Dell Inc.\n<br>\tVersion: A04\n<br>\tRelease Date: 08/19/2013\n<br>\tAddress: 0xE0000\n<br>\tRuntime Size: 128 kB\n<br>\tROM Size: 4096 kB\n<br>\tCharacteristics:\n<br>\t\tPCI is supported\n<br>\t\tPNP is supported\n<br>\t\tBIOS is upgradeable\n<br>\t\tBIOS shadowing is allowed\n<br>\t\tBoot from CD is supported\n<br>\t\tSelectable boot is supported\n<br>\t\tEDD is supported\n<br>\t\tJapanese floppy for NEC 9800 1.2 MB is supported (int 13h)\n<br>\t\tJapanese floppy for Toshiba 1.2 MB is supported (int 13h)\n<br>\t\t5.25/360 kB floppy services are supported (int 13h)\n<br>\t\t5.25/1.2 MB floppy services are supported (int 13h)\n<br>\t\t3.5/720 kB floppy services are supported (int 13h)\n<br>\t\t3.5/2.88 MB floppy services are supported (int 13h)\n<br>\t\tPrint screen service is supported (int 5h)\n<br>\t\t8042 keyboard services are supported (int 9h)\n<br>\t\tSerial services are supported (int 14h)\n<br>\t\tPrinter services are supported (int 17h)\n<br>\t\tCGA/mono video services are supported (int 10h)\n<br>\t\tACPI is supported\n<br>\t\tUSB legacy is supported\n<br>\t\tBIOS boot specification is supported\n<br>\t\tTargeted content distribution is supported\n<br>\t\tUEFI is supported\n<br>\tFirmware Revision: 1.1\n<br>\n<br>Handle 0x0001, DMI type 1, 27 bytes\n<br>System Information\n<br>\tManufacturer: Dell Inc.\n<br>\tProduct Name: Inspiron 5537\n<br>\tVersion: A04\n<br>\tSerial Number: 3X5VQX1\n<br>\tUUID: 4C4C4544-0058-3510-8056-B3C04F515831\n<br>\tWake-up Type: Power Switch\n<br>\tSKU Number: Inspiron 5537\n<br>\tFamily: 00\n<br>\n<br>Handle 0x0002, DMI type 2, 16 bytes\n<br>Base Board Information\n<br>\tManufacturer: Dell Inc.\n<br>\tProduct Name: 0RKNTK\n<br>\tVersion: A00\n<br>\tSerial Number: .3X5VQX1.CN129663A10373.\n<br>\tAsset Tag: Not Specified\n<br>\tFeatures:\n<br>\t\tBoard is a hosting board\n<br>\t\tBoard is replaceable\n<br>\tLocation In Chassis: Type2 - Board Chassis Location\n<br>\tChassis Handle: 0x0003\n<br>\tType: Motherboard\n<br>\tContained Object Handles: 0\n<br>\n<br>Handle 0x0003, DMI type 3, 23 bytes\n<br>Chassis Information\n<br>\tManufacturer: Dell Inc.\n<br>\tType: Portable\n<br>\tLock: Not Present\n<br>\tVersion: A04\n<br>\tSerial Number: 3X5VQX1\n<br>\tAsset Tag: Not Specified\n<br>\tBoot-up State: Safe\n<br>\tPower Supply State: Safe\n<br>\tThermal State: Safe\n<br>\tSecurity Status: None\n<br>\tOEM Information: 0x00000000\n<br>\tHeight: Unspecified\n<br>\tNumber Of Power Cords: 1\n<br>\tContained Elements: 0\n<br>\tSKU Number: Not Specified\n<br>\n<br>Handle 0x0004, DMI type 4, 42 bytes\n<br>Processor Information\n<br>\tSocket Designation: U3E1\n<br>\tType: Central Processor\n<br>\tFamily: Core i5\n<br>\tManufacturer: Intel(R) Corporation\n<br>\tID: 51 06 04 00 FF FB EB BF\n<br>\tSignature: Type 0, Family 6, Model 69, Stepping 1\n<br>\tFlags:\n<br>\t\tFPU (Floating-point unit on-chip)\n<br>\t\tVME (Virtual mode extension)\n<br>\t\tDE (Debugging extension)\n<br>\t\tPSE (Page size extension)\n<br>\t\tTSC (Time stamp counter)\n<br>\t\tMSR (Model specific registers)\n<br>\t\tPAE (Physical address extension)\n<br>\t\tMCE (Machine check exception)\n<br>\t\tCX8 (CMPXCHG8 instruction supported)\n<br>\t\tAPIC (On-chip APIC hardware supported)\n<br>\t\tSEP (Fast system call)\n<br>\t\tMTRR (Memory type range registers)\n<br>\t\tPGE (Page global enable)\n<br>\t\tMCA (Machine check architecture)\n<br>\t\tCMOV (Conditional move instruction supported)\n<br>\t\tPAT (Page attribute table)\n<br>\t\tPSE-36 (36-bit page size extension)\n<br>\t\tCLFSH (CLFLUSH instruction supported)\n<br>\t\tDS (Debug store)\n<br>\t\tACPI (ACPI supported)\n<br>\t\tMMX (MMX technology supported)\n<br>\t\tFXSR (FXSAVE and FXSTOR instructions supported)\n<br>\t\tSSE (Streaming SIMD extensions)\n<br>\t\tSSE2 (Streaming SIMD extensions 2)\n<br>\t\tSS (Self-snoop)\n<br>\t\tHTT (Multi-threading)\n<br>\t\tTM (Thermal monitor supported)\n<br>\t\tPBE (Pending break enabled)\n<br>\tVersion: Intel(R) Core(TM) i5-4200U CPU @ 1.60GHz\n<br>\tVoltage: 0.7 V\n<br>\tExternal Clock: 100 MHz\n<br>\tMax Speed: 2300 MHz\n<br>\tCurrent Speed: 1600 MHz\n<br>\tStatus: Populated, Enabled\n<br>\tUpgrade: <OUT OF SPEC>\n<br>\tL1 Cache Handle: 0x0009\n<br>\tL2 Cache Handle: 0x000A\n<br>\tL3 Cache Handle: 0x000B\n<br>\tSerial Number: To Be Filled By O.E.M.\n<br>\tAsset Tag: To Be Filled By O.E.M.\n<br>\tPart Number: To Be Filled By O.E.M.\n<br>\tCore Count: 2\n<br>\tCore Enabled: 2\n<br>\tThread Count: 4\n<br>\tCharacteristics:\n<br>\t\t64-bit capable\n<br>\t\tMulti-Core\n<br>\t\tHardware Thread\n<br>\t\tExecute Protection\n<br>\t\tEnhanced Virtualization\n<br>\t\tPower/Performance Control\n<br>\n<br>Handle 0x0005, DMI type 5, 20 bytes\n<br>Memory Controller Information\n<br><font color=red>\tError Detecting Method: None\n</font><br><font color=red>\tError Correcting Capabilities:\n</font><br>\t\tNone\n<br>\tSupported Interleave: One-way Interleave\n<br>\tCurrent Interleave: One-way Interleave\n<br>\tMaximum Memory Module Size: 8192 MB\n<br>\tMaximum Total Memory Size: 16384 MB\n<br>\tSupported Speeds:\n<br>\t\tOther\n<br>\tSupported Memory Types:\n<br>\t\tOther\n<br>\tMemory Module Voltage: Unknown\n<br>\tAssociated Memory Slots: 2\n<br>\t\t0x0006\n<br>\t\t0x0007\n<br><font color=red>\tEnabled Error Correcting Capabilities:\n</font><br>\t\tNone\n<br>\n<br>Handle 0x0006, DMI type 6, 12 bytes\n<br>Memory Module Information\n<br>\tSocket Designation: JDIMM1\n<br>\tBank Connections: None\n<br>\tCurrent Speed: Unknown\n<br>\tType: DIMM\n<br>\tInstalled Size: Not Installed\n<br>\tEnabled Size: Not Installed\n<br><font color=red>\tError Status: OK\n</font><br>\n<br>Handle 0x0007, DMI type 6, 12 bytes\n<br>Memory Module Information\n<br>\tSocket Designation: JDIMM2\n<br>\tBank Connections: None\n<br>\tCurrent Speed: Unknown\n<br>\tType: DIMM\n<br>\tInstalled Size: 4096 MB (Single-bank Connection)\n<br>\tEnabled Size: 4096 MB (Single-bank Connection)\n<br><font color=red>\tError Status: OK\n</font><br>\n<br>Handle 0x0008, DMI type 7, 19 bytes\n<br>Cache Information\n<br>\tSocket Designation: L1 Cache\n<br>\tConfiguration: Enabled, Not Socketed, Level 1\n<br>\tOperational Mode: Write Back\n<br>\tLocation: Internal\n<br>\tInstalled Size: 32 kB\n<br>\tMaximum Size: 32 kB\n<br>\tSupported SRAM Types:\n<br>\t\tSynchronous\n<br>\tInstalled SRAM Type: Synchronous\n<br>\tSpeed: Unknown\n<br><font color=red>\tError Correction Type: Single-bit ECC\n</font><br>\tSystem Type: Data\n<br>\tAssociativity: 8-way Set-associative\n<br>\n<br>Handle 0x0009, DMI type 7, 19 bytes\n<br>Cache Information\n<br>\tSocket Designation: L1 Cache\n<br>\tConfiguration: Enabled, Not Socketed, Level 1\n<br>\tOperational Mode: Write Back\n<br>\tLocation: Internal\n<br>\tInstalled Size: 32 kB\n<br>\tMaximum Size: 32 kB\n<br>\tSupported SRAM Types:\n<br>\t\tSynchronous\n<br>\tInstalled SRAM Type: Synchronous\n<br>\tSpeed: Unknown\n<br><font color=red>\tError Correction Type: Single-bit ECC\n</font><br>\tSystem Type: Instruction\n<br>\tAssociativity: 8-way Set-associative\n<br>\n<br>Handle 0x000A, DMI type 7, 19 bytes\n<br>Cache Information\n<br>\tSocket Designation: L2 Cache\n<br>\tConfiguration: Enabled, Not Socketed, Level 2\n<br>\tOperational Mode: Write Back\n<br>\tLocation: Internal\n<br>\tInstalled Size: 256 kB\n<br>\tMaximum Size: 256 kB\n<br>\tSupported SRAM Types:\n<br>\t\tSynchronous\n<br>\tInstalled SRAM Type: Synchronous\n<br>\tSpeed: Unknown\n<br><font color=red>\tError Correction Type: Single-bit ECC\n</font><br>\tSystem Type: Unified\n<br>\tAssociativity: 8-way Set-associative\n<br>\n<br>Handle 0x000B, DMI type 7, 19 bytes\n<br>Cache Information\n<br>\tSocket Designation: L3 Cache\n<br>\tConfiguration: Enabled, Not Socketed, Level 3\n<br>\tOperational Mode: Write Back\n<br>\tLocation: Internal\n<br>\tInstalled Size: 3072 kB\n<br>\tMaximum Size: 3072 kB\n<br>\tSupported SRAM Types:\n<br>\t\tSynchronous\n<br>\tInstalled SRAM Type: Synchronous\n<br>\tSpeed: Unknown\n<br><font color=red>\tError Correction Type: Single-bit ECC\n</font><br>\tSystem Type: Unified\n<br>\tAssociativity: 12-way Set-associative\n<br>\n<br>Handle 0x000C, DMI type 8, 9 bytes\n<br>Port Connector Information\n<br>\tInternal Reference Designator: J1A1\n<br>\tInternal Connector Type: None\n<br>\tExternal Reference Designator: Keyboard\n<br>\tExternal Connector Type: PS/2\n<br>\tPort Type: Keyboard Port\n<br>\n<br>Handle 0x000D, DMI type 8, 9 bytes\n<br>Port Connector Information\n<br>\tInternal Reference Designator: J1A1\n<br>\tInternal Connector Type: None\n<br>\tExternal Reference Designator: Mouse\n<br>\tExternal Connector Type: PS/2\n<br>\tPort Type: Mouse Port\n<br>\n<br>Handle 0x000E, DMI type 8, 9 bytes\n<br>Port Connector Information\n<br>\tInternal Reference Designator: J3A1\n<br>\tInternal Connector Type: None\n<br>\tExternal Reference Designator: USB\n<br>\tExternal Connector Type: Access Bus (USB)\n<br>\tPort Type: USB\n<br>\n<br>Handle 0x000F, DMI type 8, 9 bytes\n<br>Port Connector Information\n<br>\tInternal Reference Designator: J3A1\n<br>\tInternal Connector Type: None\n<br>\tExternal Reference Designator: USB\n<br>\tExternal Connector Type: Access Bus (USB)\n<br>\tPort Type: USB\n<br>\n<br>Handle 0x0010, DMI type 8, 9 bytes\n<br>Port Connector Information\n<br>\tInternal Reference Designator: J3A1\n<br>\tInternal Connector Type: None\n<br>\tExternal Reference Designator: USB\n<br>\tExternal Connector Type: Access Bus (USB)\n<br>\tPort Type: USB\n<br>\n<br>Handle 0x0011, DMI type 8, 9 bytes\n<br>Port Connector Information\n<br>\tInternal Reference Designator: J5A1\n<br>\tInternal Connector Type: None\n<br>\tExternal Reference Designator: USB\n<br>\tExternal Connector Type: Access Bus (USB)\n<br>\tPort Type: USB\n<br>\n<br>Handle 0x0012, DMI type 8, 9 bytes\n<br>Port Connector Information\n<br>\tInternal Reference Designator: J5A1\n<br>\tInternal Connector Type: None\n<br>\tExternal Reference Designator: Network\n<br>\tExternal Connector Type: RJ-45\n<br>\tPort Type: Network Port\n<br>\n<br>Handle 0x0013, DMI type 8, 9 bytes\n<br>Port Connector Information\n<br>\tInternal Reference Designator: J7J1\n<br>\tInternal Connector Type: On Board IDE\n<br>\tExternal Reference Designator: OnBoard Primary IDE\n<br>\tExternal Connector Type: None\n<br>\tPort Type: Other\n<br>\n<br>Handle 0x0014, DMI type 8, 9 bytes\n<br>Port Connector Information\n<br>\tInternal Reference Designator: J30\n<br>\tInternal Connector Type: None\n<br>\tExternal Reference Designator: Microphone In\n<br>\tExternal Connector Type: Mini Jack (headphones)\n<br>\tPort Type: Audio Port\n<br>\n<br>Handle 0x0015, DMI type 8, 9 bytes\n<br>Port Connector Information\n<br>\tInternal Reference Designator: J30\n<br>\tInternal Connector Type: None\n<br>\tExternal Reference Designator: Line In\n<br>\tExternal Connector Type: Mini Jack (headphones)\n<br>\tPort Type: Audio Port\n<br>\n<br>Handle 0x0016, DMI type 8, 9 bytes\n<br>Port Connector Information\n<br>\tInternal Reference Designator: J30\n<br>\tInternal Connector Type: None\n<br>\tExternal Reference Designator: Speaker Out\n<br>\tExternal Connector Type: Mini Jack (headphones)\n<br>\tPort Type: Audio Port\n<br>\n<br>Handle 0x0017, DMI type 9, 17 bytes\n<br>System Slot Information\n<br>\tDesignation: J5C1\n<br>\tType: x16 PCI Express x16\n<br>\tCurrent Usage: Available\n<br>\tLength: Other\n<br>\tID: 1\n<br>\tCharacteristics:\n<br>\t\tPME signal is supported\n<br>\t\tHot-plug devices are supported\n<br>\tBus Address: 0000:00:01.0\n<br>\n<br>Handle 0x0018, DMI type 9, 17 bytes\n<br>System Slot Information\n<br>\tDesignation: J6C1\n<br>\tType: x1 PCI Express x1\n<br>\tCurrent Usage: Available\n<br>\tLength: Other\n<br>\tID: 2\n<br>\tCharacteristics:\n<br>\t\tPME signal is supported\n<br>\t\tHot-plug devices are supported\n<br>\tBus Address: 0000:00:1c.0\n<br>\n<br>Handle 0x0019, DMI type 9, 17 bytes\n<br>System Slot Information\n<br>\tDesignation: J6C2\n<br>\tType: x1 PCI Express x1\n<br>\tCurrent Usage: Available\n<br>\tLength: Other\n<br>\tID: 3\n<br>\tCharacteristics:\n<br>\t\tPME signal is supported\n<br>\t\tHot-plug devices are supported\n<br>\tBus Address: 0000:00:1c.1\n<br>\n<br>Handle 0x001A, DMI type 9, 17 bytes\n<br>System Slot Information\n<br>\tDesignation: J6D2\n<br>\tType: x1 PCI Express x1\n<br>\tCurrent Usage: Available\n<br>\tLength: Other\n<br>\tID: 4\n<br>\tCharacteristics:\n<br>\t\tPME signal is supported\n<br>\t\tHot-plug devices are supported\n<br>\tBus Address: 0000:00:1c.2\n<br>\n<br>Handle 0x001B, DMI type 9, 17 bytes\n<br>System Slot Information\n<br>\tDesignation: J7C1\n<br>\tType: x1 PCI Express x1\n<br>\tCurrent Usage: Available\n<br>\tLength: Other\n<br>\tID: 5\n<br>\tCharacteristics:\n<br>\t\tPME signal is supported\n<br>\t\tHot-plug devices are supported\n<br>\tBus Address: 0000:00:1c.3\n<br>\n<br>Handle 0x001C, DMI type 9, 17 bytes\n<br>System Slot Information\n<br>\tDesignation: J7D2\n<br>\tType: x1 PCI Express x1\n<br>\tCurrent Usage: Available\n<br>\tLength: Other\n<br>\tID: 6\n<br>\tCharacteristics:\n<br>\t\tPME signal is supported\n<br>\t\tHot-plug devices are supported\n<br>\tBus Address: 0000:00:1c.4\n<br>\n<br>Handle 0x001D, DMI type 9, 17 bytes\n<br>System Slot Information\n<br>\tDesignation: J8C1\n<br>\tType: x1 PCI Express x1\n<br>\tCurrent Usage: Available\n<br>\tLength: Other\n<br>\tID: 7\n<br>\tCharacteristics:\n<br>\t\tPME signal is supported\n<br>\t\tHot-plug devices are supported\n<br>\tBus Address: 0000:00:1c.5\n<br>\n<br>Handle 0x001E, DMI type 9, 17 bytes\n<br>System Slot Information\n<br>\tDesignation: J8C2\n<br>\tType: x16 PCI Express x16\n<br>\tCurrent Usage: Available\n<br>\tLength: Other\n<br>\tID: 8\n<br>\tCharacteristics:\n<br>\t\tPME signal is supported\n<br>\t\tHot-plug devices are supported\n<br>\tBus Address: 0000:00:1c.7\n<br>\n<br>Handle 0x001F, DMI type 10, 6 bytes\n<br>On Board Device Information\n<br>\tType: Video\n<br>\tStatus: Enabled\n<br>\tDescription: Intel Video Graphics Controller\n<br>\n<br>Handle 0x0020, DMI type 11, 5 bytes\n<br>OEM Strings\n<br>\tString 1: Dell System\n<br>\tString 2: 1[05EA]\n<br>\tString 3: 3[1.3]\n<br>\tString 4: 4[0001]\n<br>\tString 5: 5[0000]\n<br>\tString 6: 6[D0, D4, D8, DA, DE]\n<br>\tString 7: 7[]\n<br>\tString 8: 8[]\n<br>\tString 9: 9[]\n<br>\tString 10: 10[A04]\n<br>\tString 11: 11[]\n<br>\tString 12: 12[]\n<br>\tString 13: 13[P28F]\n<br>\tString 14: 14[2]\n<br>\tString 15: 15[0]\n<br>\tString 16: String16 for Original Equipment Manufacturer\n<br>\n<br>Handle 0x0021, DMI type 12, 5 bytes\n<br>System Configuration Options\n<br>\tOption 1: String1 for Type12 Equipment Manufacturer\n<br>\tOption 2: String2 for Type12 Equipment Manufacturer\n<br>\tOption 3: String3 for Type12 Equipment Manufacturer\n<br>\tOption 4: String4 for Type12 Equipment Manufacturer\n<br>\n<br>Handle 0x0022, DMI type 13, 22 bytes\n<br>BIOS Language Information\n<br>\tLanguage Description Format: Long\n<br>\tInstallable Languages: 4\n<br>\t\ten|US|iso8859-1\n<br>\t\tfr|CA|iso8859-1\n<br>\t\tja|JP|unicode\n<br>\t\tzh|TW|unicode\n<br>\tCurrently Installed Language: en|US|iso8859-1\n<br>\n<br>Handle 0x0023, DMI type 16, 23 bytes\n<br>Physical Memory Array\n<br>\tLocation: System Board Or Motherboard\n<br>\tUse: System Memory\n<br><font color=red>\tError Correction Type: None\n</font><br>\tMaximum Capacity: 16 GB\n<br><font color=red>\tError Information Handle: 0x0027\n</font><br>\tNumber Of Devices: 2\n<br>\n<br>Handle 0x0024, DMI type 17, 34 bytes\n<br>Memory Device\n<br>\tArray Handle: 0x0023\n<br><font color=red>\tError Information Handle: Not Provided\n</font><br>\tTotal Width: Unknown\n<br>\tData Width: Unknown\n<br>\tSize: No Module Installed\n<br>\tForm Factor: DIMM\n<br>\tSet: None\n<br>\tLocator: JDIMM1\n<br>\tBank Locator: Not Specified\n<br>\tType: Unknown\n<br>\tType Detail: Unknown\n<br>\tSpeed: Unknown\n<br>\tManufacturer: Empty\n<br>\tSerial Number: Empty\n<br>\tAsset Tag: Unknown\n<br>\tPart Number: Empty\n<br>\tRank: Unknown\n<br>\tConfigured Clock Speed: Unknown\n<br>\n<br>Handle 0x0025, DMI type 17, 34 bytes\n<br>Memory Device\n<br>\tArray Handle: 0x0023\n<br><font color=red>\tError Information Handle: 0x0026\n</font><br>\tTotal Width: 64 bits\n<br>\tData Width: 64 bits\n<br>\tSize: 4096 MB\n<br>\tForm Factor: SODIMM\n<br>\tSet: None\n<br>\tLocator: JDIMM2\n<br>\tBank Locator: Not Specified\n<br>\tType: DDR3\n<br>\tType Detail: Synchronous\n<br>\tSpeed: 1600 MHz\n<br>\tManufacturer: Samsung\n<br>\tSerial Number: 966707B7\n<br>\tAsset Tag: Unknown\n<br>\tPart Number: M471B5173DB0-YK0  \n<br>\tRank: 1\n<br>\tConfigured Clock Speed: 1600 MHz\n<br>\n<br>Handle 0x0026, DMI type 18, 23 bytes\n<br><font color=red>32-bit Memory Error Information\n</font><br>\tType: OK\n<br>\tGranularity: Unknown\n<br>\tOperation: Unknown\n<br>\tVendor Syndrome: Unknown\n<br>\tMemory Array Address: Unknown\n<br>\tDevice Address: Unknown\n<br>\tResolution: Unknown\n<br>\n<br>Handle 0x0027, DMI type 18, 23 bytes\n<br><font color=red>32-bit Memory Error Information\n</font><br>\tType: OK\n<br>\tGranularity: Unknown\n<br>\tOperation: Unknown\n<br>\tVendor Syndrome: Unknown\n<br>\tMemory Array Address: Unknown\n<br>\tDevice Address: Unknown\n<br>\tResolution: Unknown\n<br>\n<br>Handle 0x0028, DMI type 19, 31 bytes\n<br>Memory Array Mapped Address\n<br>\tStarting Address: 0x00000000000\n<br>\tEnding Address: 0x000FFFFFFFF\n<br>\tRange Size: 4 GB\n<br>\tPhysical Array Handle: 0x0023\n<br>\tPartition Width: 2\n<br>\n<br>Handle 0x0029, DMI type 20, 35 bytes\n<br>Memory Device Mapped Address\n<br>\tStarting Address: 0x00000000000\n<br>\tEnding Address: 0x000FFFFFFFF\n<br>\tRange Size: 4 GB\n<br>\tPhysical Device Handle: 0x0025\n<br>\tMemory Array Mapped Address Handle: 0x0028\n<br>\tPartition Row Position: 1\n<br>\tInterleave Position: 2\n<br>\tInterleaved Data Depth: 1\n<br>\n<br>Handle 0x002A, DMI type 21, 7 bytes\n<br>Built-in Pointing Device\n<br>\tType: Touch Pad\n<br>\tInterface: Bus Mouse\n<br>\tButtons: 2\n<br>\n<br>Handle 0x002B, DMI type 22, 26 bytes\n<br>Portable Battery\n<br>\tLocation: Sys. Battery Bay\n<br>\tManufacturer: SANYO\n<br>\tName: DELL 6HY5938S\n<br>\tChemistry: Lithium Ion\n<br>\tDesign Capacity: 60000 mWh\n<br>\tDesign Voltage: 11100 mV\n<br>\tSBDS Version: 1.0\n<br><font color=red>\tMaximum Error: 100%\n</font><br>\tSBDS Serial Number: 0001\n<br>\tSBDS Manufacture Date: 2009-01-01\n<br>\tOEM-specific Information: 0x0000FFFF\n<br>\n<br>Handle 0x002C, DMI type 24, 5 bytes\n<br>Hardware Security\n<br>\tPower-On Password Status: Disabled\n<br>\tKeyboard Password Status: Disabled\n<br>\tAdministrator Password Status: Disabled\n<br>\tFront Panel Reset Status: Disabled\n<br>\n<br>Handle 0x002D, DMI type 26, 22 bytes\n<br>Voltage Probe\n<br>\tDescription: Voltage Probe\n<br>\tLocation: Processor\n<br>\tStatus: OK\n<br>\tMaximum Value: Unknown\n<br>\tMinimum Value: Unknown\n<br>\tResolution: Unknown\n<br>\tTolerance: Unknown\n<br>\tAccuracy: Unknown\n<br>\tOEM-specific Information: 0x00000000\n<br>\tNominal Value: Unknown\n<br>\n<br>Handle 0x002E, DMI type 27, 14 bytes\n<br>Cooling Device\n<br>\tTemperature Probe Handle: 0x002F\n<br>\tType: Fan\n<br>\tStatus: OK\n<br>\tOEM-specific Information: 0x00000000\n<br>\tNominal Speed: 0 rpm\n<br>\n<br>Handle 0x002F, DMI type 28, 22 bytes\n<br>Temperature Probe\n<br>\tDescription: Temperature Probe\n<br>\tLocation: Processor\n<br>\tStatus: OK\n<br>\tMaximum Value: Unknown\n<br>\tMinimum Value: Unknown\n<br>\tResolution: Unknown\n<br>\tTolerance: Unknown\n<br>\tAccuracy: Unknown\n<br>\tOEM-specific Information: 0x00000000\n<br>\tNominal Value: 2594.0 deg C\n<br>\n<br>Handle 0x0030, DMI type 29, 24 bytes\n<br>Electrical Current Probe\n<br>\tDescription: Electrical Current Probe\n<br>\tLocation: Processor\n<br>\tStatus: OK\n<br>\tMaximum Value: Unknown\n<br>\tMinimum Value: Unknown\n<br>\tResolution: Unknown\n<br>\tTolerance: Unknown\n<br>\tAccuracy: Unknown\n<br>\tOEM-specific Information: 0x00000000\n<br>\tNominal Value: 0.000 A\n<br>\n<br>Handle 0x0031, DMI type 32, 20 bytes\n<br>System Boot Information\n<br>\tStatus: No errors detected\n<br>\n<br>Handle 0x0032, DMI type 38, 18 bytes\n<br>IPMI Device Information\n<br>\tInterface Type: Unknown\n<br>\tSpecification Version: 2.0\n<br>\tI2C Slave Address: 0x00\n<br>\tNV Storage Device: Not Present\n<br>\tBase Address: 0x0000000000000000 (Memory-mapped)\n<br>\tRegister Spacing: <OUT OF SPEC>\n<br>\n<br>Handle 0x0033, DMI type 40, 18 bytes\n<br>Additional Information 1\n<br>\tReferenced Handle: 0x0017\n<br>\tReferenced Offset: 0x05\n<br>\tString: PCIExpressx16\n<br>\tValue: 0xaa\n<br>Additional Information 2\n<br>\tReferenced Handle: 0x0000\n<br>\tReferenced Offset: 0x05\n<br>\tString: Compiler Version: VC 9.0\n<br>\tValue: 0x05dc\n<br>\n<br>Handle 0x0034, DMI type 41, 11 bytes\n<br>Onboard Device\n<br>\tReference Designation: Hanksville Gbe Lan Connection\n<br>\tType: Ethernet\n<br>\tStatus: Enabled\n<br>\tType Instance: 1\n<br>\tBus Address: 0000:00:00.1\n<br>\n<br>Handle 0x0035, DMI type 128, 8 bytes\n<br>OEM-specific Type\n<br>\tHeader and Data:\n<br>\t\t80 08 35 00 55 AA 55 AA\n<br>\tStrings:\n<br>\t\tOem Test 1\n<br>\t\tOem Test 2\n<br>\n<br>Handle 0x0036, DMI type 129, 8 bytes\n<br>OEM-specific Type\n<br>\tHeader and Data:\n<br>\t\t81 08 36 00 01 01 02 01\n<br>\tStrings:\n<br>\t\tIntel_ASF\n<br>\t\tIntel_ASF_001\n<br>\n<br>Handle 0x0037, DMI type 130, 20 bytes\n<br>OEM-specific Type\n<br>\tHeader and Data:\n<br>\t\t82 14 37 00 24 41 4D 54 01 01 01 01 01 A5 1F 02\n<br>\t\t00 00 00 00\n<br>\n<br>Handle 0x0038, DMI type 136, 6 bytes\n<br>OEM-specific Type\n<br>\tHeader and Data:\n<br>\t\t88 06 38 00 FF FF\n<br>\n<br>Handle 0x0039, DMI type 176, 5 bytes\n<br>OEM-specific Type\n<br>\tHeader and Data:\n<br>\t\tB0 05 39 00 00\n<br>\n<br>Handle 0x003A, DMI type 177, 12 bytes\n<br>OEM-specific Type\n<br>\tHeader and Data:\n<br>\t\tB1 0C 3A 00 1A 00 00 00 00 00 00 00\n<br>\n<br>Handle 0x003B, DMI type 202, 29 bytes\n<br>OEM-specific Type\n<br>\tHeader and Data:\n<br>\t\tCA 1D 3B 00 B2 00 D4 03 00 00 00 20 00 00 80 00\n<br>\t\t00 21 00 01 80 00 00 FF FF 00 00 00 00\n<br>\n<br>Handle 0x003C, DMI type 208, 10 bytes\n<br>OEM-specific Type\n<br>\tHeader and Data:\n<br>\t\tD0 0A 3C 00 02 06 FE 00 EA 05\n<br>\n<br>Handle 0x003D, DMI type 210, 12 bytes\n<br>OEM-specific Type\n<br>\tHeader and Data:\n<br>\t\tD2 0C 3D 00 00 00 00 02 02 00 00 02\n<br>\n<br>Handle 0x003E, DMI type 212, 17 bytes\n<br>OEM-specific Type\n<br>\tHeader and Data:\n<br>\t\tD4 11 3E 00 70 00 71 00 00 10 2D 00 00 00 00 00\n<br>\t\t00\n<br>\n<br>Handle 0x003F, DMI type 216, 9 bytes\n<br>OEM-specific Type\n<br>\tHeader and Data:\n<br>\t\tD8 09 3F 00 01 02 01 F0 03\n<br>\tStrings:\n<br>\t\tIntel Corp.\n<br>\t\t1264\n<br>\n<br>Handle 0x0040, DMI type 217, 8 bytes\n<br>OEM-specific Type\n<br>\tHeader and Data:\n<br>\t\tD9 08 40 00 01 02 02 02\n<br>\tStrings:\n<br>\t\tKeyboard\n<br>\t\tKeyboard\n<br>\n<br>Handle 0xDA00, DMI type 218, 227 bytes\n<br>OEM-specific Type\n<br>\tHeader and Data:\n<br>\t\tDA E3 00 DA B2 00 91 5F 1F 7F 00 24 40 1D 02 01\n<br>\t\t00 25 40 1D 02 00 00 2D 00 03 80 02 00 2E 00 03\n<br>\t\t80 00 00 6E 00 03 80 01 00 95 00 19 02 01 00 96\n<br>\t\t00 19 02 00 00 9B 00 5C 00 00 00 9C 00 5C 00 01\n<br>\t\t00 EA 00 6D 00 01 00 EB 00 6D 00 00 00 14 01 25\n<br>\t\t02 00 00 15 01 25 02 01 00 16 01 25 02 02 00 4A\n<br>\t\t01 A7 01 00 00 4B 01 A7 01 01 00 52 01 1E 02 01\n<br>\t\t00 53 01 1E 02 00 00 75 01 23 02 00 00 76 01 23\n<br>\t\t02 01 00 7B 01 20 02 00 00 7C 01 20 02 01 00 7F\n<br>\t\t01 1F 02 00 00 80 01 1F 02 01 00 89 01 15 02 00\n<br>\t\t00 8A 01 15 02 01 00 93 01 24 02 00 00 94 01 24\n<br>\t\t02 01 00 7D 00 02 80 00 00 00 FE 01 80 00 00 01\n<br>\t\tFE 01 80 01 00 A5 02 04 80 01 00 A6 02 04 80 00\n<br>\t\t00 2D 01 05 80 01 00 2E 01 05 80 00 00 FF FF 00\n<br>\t\t00 00 00\n<br>\n<br>Handle 0xDA01, DMI type 218, 239 bytes\n<br>OEM-specific Type\n<br>\tHeader and Data:\n<br>\t\tDA EF 01 DA B2 00 91 FF FF FF FF 46 01 17 02 00\n<br>\t\t00 47 01 17 02 01 00 ED 00 A3 01 00 00 F0 00 A3\n<br>\t\t01 01 00 37 01 07 80 00 00 38 01 07 80 01 00 39\n<br>\t\t01 07 80 02 00 3C 03 07 80 03 00 0E 01 1A 02 01\n<br>\t\t00 0F 01 1A 02 00 00 3D 03 08 80 00 00 3E 03 08\n<br>\t\t80 01 00 4F 03 09 80 01 00 2D 02 0A 80 02 00 2E\n<br>\t\t02 0A 80 01 00 57 03 0B 80 00 00 58 03 0B 80 01\n<br>\t\t00 00 00 00 00 00 00 00 00 00 00 00 00 00 00 00\n<br>\t\t00 00 00 00 00 00 00 00 00 00 00 00 00 00 00 00\n<br>\t\t00 00 00 00 00 00 00 00 00 00 00 00 00 00 00 00\n<br>\t\t00 00 00 00 00 00 00 00 00 00 00 00 00 00 00 00\n<br>\t\t00 00 00 00 00 00 00 00 00 00 00 00 00 00 00 00\n<br>\t\t00 00 00 00 00 00 00 00 00 00 00 00 00 00 00 00\n<br>\t\t00 00 00 00 00 00 00 00 00 00 00 00 00 00 00 00\n<br>\t\t00 00 00 00 00 00 00 00 00 FF FF 00 00 00 00\n<br>\n<br>Handle 0xDA02, DMI type 219, 11 bytes\n<br>OEM-specific Type\n<br>\tHeader and Data:\n<br>\t\tDB 0B 02 DA 02 01 02 03 FF 04 05\n<br>\tStrings:\n<br>\t\t00h\n<br>\t\t00h\n<br>\t\t00h\n<br>\t\t00h\n<br>\t\t00h\n<br>\n<br>Handle 0xDA03, DMI type 220, 22 bytes\n<br>OEM-specific Type\n<br>\tHeader and Data:\n<br>\t\tDC 16 03 DA 01 F0 00 00 02 F0 00 00 00 00 03 F0\n<br>\t\t04 F0 00 00 00 00\n<br>\n<br>Handle 0xDA04, DMI type 221, 19 bytes\n<br>OEM-specific Type\n<br>\tHeader and Data:\n<br>\t\tDD 13 04 DA 00 00 00 00 00 00 00 00 00 00 00 00\n<br>\t\t00 00 00\n<br>\n<br>Handle 0xDA05, DMI type 221, 12 bytes\n<br>OEM-specific Type\n<br>\tHeader and Data:\n<br>\t\tDD 0C 05 DA 01 01 00 01 04 00 00 00\n<br>\tStrings:\n<br>\t\tReference Code - Intel Rapid Start\n<br>\n<br>Handle 0xDA06, DMI type 222, 16 bytes\n<br>OEM-specific Type\n<br>\tHeader and Data:\n<br>\t\tDE 10 06 DA 01 02 FF FF 00 00 00 00 00 00 00 00\n<br>\n<br>Handle 0xDA07, DMI type 127, 4 bytes\n<br>End Of Table\n<br>\n<br>", "hostname": "isoft_lp\n<br>", "modules": "bridge 106132 0 - Live 0xffffffffa0447000\n<br>stp 1821 1 bridge, Live 0xffffffffa0088000\n<br>llc 3761 2 bridge,stp, Live 0xffffffffa0031000\n<br>nls_utf8 1576 1 - Live 0xffffffffa000b000\n<br>ntfs 87071 1 - Live 0xffffffffa02ef000\n<br>drbg 24901 1 - Live 0xffffffffa0318000\n<br>ansi_cprng 4068 0 - Live 0xffffffffa003e000\n<br>ctr 4031 2 - Live 0xffffffffa0028000\n<br>ccm 8624 2 - Live 0xffffffffa00d3000\n<br>rfcomm 51422 2 - Live 0xffffffffa0439000\n<br>bnep 13213 2 - Live 0xffffffffa112c000\n<br>nvram 5818 0 - Live 0xffffffffa110a000\n<br>msr 2765 0 - Live 0xffffffffa1106000\n<br>intel_rapl 13149 0 - Live 0xffffffffa10e6000\n<br>iosf_mbi 3162 1 intel_rapl, Live 0xffffffffa10d6000\n<br>x86_pkg_temp_thermal 7159 0 - Live 0xffffffffa10a5000\n<br>intel_powerclamp 8118 0 - Live 0xffffffffa108a000\n<br>iTCO_wdt 5988 0 - Live 0xffffffffa1085000\n<br>dell_wmi 3650 0 - Live 0xffffffffa1081000\n<br>iTCO_vendor_support 2097 1 iTCO_wdt, Live 0xffffffffa107d000\n<br>sparse_keymap 3282 1 dell_wmi, Live 0xffffffffa1079000\n<br>dell_laptop 14556 0 - Live 0xffffffffa106e000\n<br>coretemp 6364 0 - Live 0xffffffffa105a000\n<br>dcdbas 6599 1 dell_laptop, Live 0xffffffffa1054000\n<br>kvm_intel 155042 0 - Live 0xffffffffa0f98000\n<br>dell_smm_hwmon 7336 0 - Live 0xffffffffa0f90000\n<br>kvm 438539 1 kvm_intel, Live 0xffffffffa0d50000\n<br>irqbypass 2872 1 kvm, Live 0xffffffffa0d42000\n<br>crct10dif_pclmul 4580 0 - Live 0xffffffffa0d31000\n<br>crc32_pclmul 3059 0 - Live 0xffffffffa0d2d000\n<br>aesni_intel 158554 4 - Live 0xffffffffa0c59000\n<br>aes_x86_64 7631 1 aesni_intel, Live 0xffffffffa0c45000\n<br>lrw 3733 1 aesni_intel, Live 0xffffffffa0c37000\n<br>gf128mul 5930 1 lrw, Live 0xffffffffa0c21000\n<br>glue_helper 4021 1 aesni_intel, Live 0xffffffffa0c11000\n<br>ablk_helper 2140 1 aesni_intel, Live 0xffffffffa0c01000\n<br>cryptd 8585 2 aesni_intel,ablk_helper, Live 0xffffffffa0be5000\n<br>rtsx_usb_ms 10664 0 - Live 0xffffffffa0bde000\n<br>memstick 7504 1 rtsx_usb_ms, Live 0xffffffffa0bd8000\n<br>uvcvideo 75645 0 - Live 0xffffffffa0bbe000\n<br>dell_led 2772 0 - Live 0xffffffffa0bba000\n<br>snd_hda_codec_hdmi 40694 1 - Live 0xffffffffa0baa000\n<br>snd_hda_codec_realtek 60989 1 - Live 0xffffffffa0b92000\n<br>videobuf2_vmalloc 5094 1 uvcvideo, Live 0xffffffffa0b8d000\n<br>videobuf2_memops 1993 1 videobuf2_vmalloc, Live 0xffffffffa0b89000\n<br>snd_hda_codec_generic 58955 1 snd_hda_codec_realtek, Live 0xffffffffa0b73000\n<br>videobuf2_v4l2 16015 1 uvcvideo, Live 0xffffffffa0b6a000\n<br>videobuf2_core 20093 2 uvcvideo,videobuf2_v4l2, Live 0xffffffffa0b61000\n<br>v4l2_common 3726 1 videobuf2_v4l2, Live 0xffffffffa0b5d000\n<br>videodev 136145 4 uvcvideo,videobuf2_v4l2,videobuf2_core,v4l2_common, Live 0xffffffffa0b2e000\n<br>snd_hda_intel 25834 5 - Live 0xffffffffa0b12000\n<br>media 12197 2 uvcvideo,videodev, Live 0xffffffffa0b0b000\n<br>snd_hda_codec 93989 4 snd_hda_codec_hdmi,snd_hda_codec_realtek,snd_hda_codec_generic,snd_hda_intel, Live 0xffffffffa0ac3000\n<br>ath3k 9165 0 - Live 0xffffffffa0ab5000\n<br>btusb 32312 0 - Live 0xffffffffa0a9b000\n<br>btrtl 4896 1 btusb, Live 0xffffffffa0a94000\n<br>btbcm 6367 1 btusb, Live 0xffffffffa0a87000\n<br>btintel 6840 1 btusb, Live 0xffffffffa0a80000\n<br>vfat 10095 1 - Live 0xffffffffa0a77000\n<br>fat 51874 1 vfat, Live 0xffffffffa0a64000\n<br>arc4 2232 2 - Live 0xffffffffa0a60000\n<br>snd_hda_core 40626 5 snd_hda_codec_hdmi,snd_hda_codec_realtek,snd_hda_codec_generic,snd_hda_intel,snd_hda_codec, Live 0xffffffffa0a3c000\n<br>bluetooth 429153 30 rfcomm,bnep,ath3k,btusb,btrtl,btbcm,btintel, Live 0xffffffffa092e000\n<br>ath9k 89041 0 - Live 0xffffffffa090e000\n<br>ath9k_common 22707 1 ath9k, Live 0xffffffffa0903000\n<br>ath9k_hw 410966 2 ath9k,ath9k_common, Live 0xffffffffa0890000\n<br>snd_hwdep 6122 1 snd_hda_codec, Live 0xffffffffa0884000\n<br>ath 18898 3 ath9k,ath9k_common,ath9k_hw, Live 0xffffffffa087b000\n<br>mac80211 541273 1 ath9k, Live 0xffffffffa07cd000\n<br>snd_seq 50322 0 - Live 0xffffffffa07a5000\n<br>snd_seq_device 3496 1 snd_seq, Live 0xffffffffa079d000\n<br>r8169 69400 0 - Live 0xffffffffa0785000\n<br>cfg80211 444336 4 ath9k,ath9k_common,ath,mac80211, Live 0xffffffffa06ed000\n<br>mii 4291 1 r8169, Live 0xffffffffa06e8000\n<br>joydev 10279 0 - Live 0xffffffffa06e1000\n<br>mousedev 10824 0 - Live 0xffffffffa06da000\n<br>input_leds 3150 0 - Live 0xffffffffa06d6000\n<br>snd_pcm 79448 4 snd_hda_codec_hdmi,snd_hda_intel,snd_hda_codec,snd_hda_core, Live 0xffffffffa06b8000\n<br>efi_pstore 4493 0 - Live 0xffffffffa06b3000\n<br>mei_me 21176 0 - Live 0xffffffffa06a2000\n<br>battery 7818 0 - Live 0xffffffffa069c000\n<br>snd_timer 19671 2 snd_seq,snd_pcm, Live 0xffffffffa0688000\n<br>snd 58925 20 snd_hda_codec_hdmi,snd_hda_codec_realtek,snd_hda_codec_generic,snd_hda_intel,snd_hda_codec,snd_hwdep,snd_seq,snd_seq_device,snd_pcm,snd_timer, Live 0xffffffffa0658000\n<br>ac 3827 0 - Live 0xffffffffa0650000\n<br>soundcore 5347 1 snd, Live 0xffffffffa0646000\n<br>efivars 7745 1 efi_pstore, Live 0xffffffffa0641000\n<br>mei 76227 1 mei_me, Live 0xffffffffa0625000\n<br>mac_hid 3505 0 - Live 0xffffffffa0615000\n<br>evdev 12055 17 - Live 0xffffffffa060e000\n<br>soc_button_array 2370 0 - Live 0xffffffffa0326000\n<br>shpchp 24409 0 - Live 0xffffffffa05ed000\n<br>lpc_ich 14432 0 - Live 0xffffffffa05e4000\n<br>i2c_i801 12664 0 - Live 0xffffffffa05dc000\n<br>dell_rbtn 3841 0 - Live 0xffffffffa0169000\n<br>rfkill 15626 9 dell_laptop,bluetooth,cfg80211,dell_rbtn, Live 0xffffffffa017f000\n<br>nfsd 286168 1 - Live 0xffffffffa0527000\n<br>auth_rpcgss 46794 1 nfsd, Live 0xffffffffa051a000\n<br>oid_registry 2499 1 auth_rpcgss, Live 0xffffffffa0117000\n<br>nfs_acl 2975 1 nfsd, Live 0xffffffffa010c000\n<br>lockd 74031 1 nfsd, Live 0xffffffffa0506000\n<br>grace 2050 2 nfsd,lockd, Live 0xffffffffa002b000\n<br>sunrpc 255449 7 nfsd,auth_rpcgss,nfs_acl,lockd, Live 0xffffffffa04c6000\n<br>sch_fq_codel 8234 6 - Live 0xffffffffa00e6000\n<br>ip_tables 16919 0 - Live 0xffffffffa0104000\n<br>x_tables 16360 1 ip_tables, Live 0xffffffffa00dd000\n<br>rtsx_usb_sdmmc 17671 0 - Live 0xffffffffa0076000\n<br>led_class 4306 5 dell_laptop,dell_led,ath9k,input_leds,rtsx_usb_sdmmc, Live 0xffffffffa0036000\n<br>mmc_core 99756 1 rtsx_usb_sdmmc, Live 0xffffffffa012d000\n<br>rtsx_usb 11855 2 rtsx_usb_ms,rtsx_usb_sdmmc, Live 0xffffffffa0049000\n<br>hid_multitouch 10696 0 - Live 0xffffffffa0024000\n<br>hid_generic 1385 0 - Live 0xffffffffa0009000\n<br>amdkfd 97728 1 - Live 0xffffffffa04ad000\n<br>amd_iommu_v2 7339 1 amdkfd, Live 0xffffffffa04a7000\n<br>ehci_pci 4359 0 - Live 0xffffffffa04a2000\n<br>ehci_hcd 62980 1 ehci_pci, Live 0xffffffffa048c000\n<br>crc32c_intel 13318 2 - Live 0xffffffffa046c000\n<br>i915 1110087 31 - Live 0xffffffffa0328000\n<br>radeon 1447312 1 - Live 0xffffffffa018c000\n<br>serio_raw 5130 0 - Live 0xffffffffa0323000\n<br>sr_mod 13719 0 - Live 0xffffffffa0184000\n<br>cdrom 42884 1 sr_mod, Live 0xffffffffa0173000\n<br>intel_gtt 12423 1 i915, Live 0xffffffffa016b000\n<br>i2c_algo_bit 5456 2 i915,radeon, Live 0xffffffffa0166000\n<br>sd_mod 31327 5 - Live 0xffffffffa0159000\n<br>ttm 71130 1 radeon, Live 0xffffffffa011a000\n<br>wmi 7650 2 dell_wmi,dell_led, Live 0xffffffffa0114000\n<br>xhci_pci 4842 0 - Live 0xffffffffa010f000\n<br>drm_kms_helper 95434 2 i915,radeon, Live 0xffffffffa00eb000\n<br>drm 272274 17 i915,radeon,ttm,drm_kms_helper, Live 0xffffffffa008f000\n<br>i2c_core 40919 8 v4l2_common,videodev,i2c_i801,i915,radeon,i2c_algo_bit,drm_kms_helper,drm, Live 0xffffffffa007d000\n<br>xhci_hcd 150708 1 xhci_pci, Live 0xffffffffa004d000\n<br>video 24997 3 dell_wmi,dell_laptop,i915, Live 0xffffffffa0041000\n<br>dm_mirror 13547 0 - Live 0xffffffffa0039000\n<br>dm_region_hash 7283 1 dm_mirror, Live 0xffffffffa0033000\n<br>dm_log 8651 2 dm_mirror,dm_region_hash, Live 0xffffffffa002d000\n<br>dm_mod 89849 2 dm_mirror,dm_log, Live 0xffffffffa000d000\n<br>autofs4 28905 2 - Live 0xffffffffa0000000\n<br>"}, "absolute_path": null, "operations_failed": 0, "results_dir": "/home/isoft_lp/Github/Autotest_client/client/Result-tmp/results/default", "operations_pass_rate": 100.0, "job": {"end": 1466559483, "status_code": "GOOD", "start": 1466559141, "duration": 342, "message": "", "localtime": "6\u6708 22 09:32:21"}, "operations_passed": 1}